LICENSE
MANIFEST.in
README.rst
git_ls_date.py
setup.py
git_ls_date.egg-info/PKG-INFO
git_ls_date.egg-info/SOURCES.txt
git_ls_date.egg-info/dependency_links.txt
git_ls_date.egg-info/entry_points.txt
git_ls_date.egg-info/top_level.txt